libfurc/__init__.py
libfurc/account.py
libfurc/archive.py
libfurc/base.py
libfurc/client.py
libfurc/colors.py
libfurc/dream.py
libfurc/exceptions.py
libfurc/fox5.py
libfurc/furcbuffer.py
libfurc/particles.py
libfurc-0.1.4.dist-info/METADATA
libfurc-0.1.4.dist-info/WHEEL
libfurc-0.1.4.dist-info/top_level.txt
libfurc-0.1.4.dist-info/RECORD
