Metadata-Version: 2.1
Name: libfurc
Version: 0.1.4
Summary: A library for handling Furcadia things.
Home-page: https://github.com/FelixWolf/libFurc
Author: Félix
Author-email: felix.wolfz@gmail.com
Classifier: Development Status :: 3 - Alpha
Classifier: Intended Audience :: Developers
Classifier: Natural Language :: English
Classifier: Operating System :: OS Independent
Classifier: Programming Language :: Python
Classifier: Programming Language :: Python :: 3
Classifier: License :: OSI Approved :: zlib/libpng License
Classifier: Topic :: Software Development :: Libraries
